makru_langc_new/__init__.py
makru_langc_new-0.1.0a1.dist-info/entry_points.txt
makru_langc_new-0.1.0a1.dist-info/LICENSE
makru_langc_new-0.1.0a1.dist-info/WHEEL
makru_langc_new-0.1.0a1.dist-info/METADATA
makru_langc_new-0.1.0a1.dist-info/RECORD
